Metadata-Version: 2.4
Name: adafruit-circuitpython-qmc5883p
Version: 1.0.1
Summary: CircuitPython driver for the Adafruit QMC5883P - Triple Axis Magnetometer - STEMMA QT
Author-email: Adafruit Industries <circuitpython@adafruit.com>
License: MIT
Project-URL: Homepage, https://github.com/adafruit/Adafruit_CircuitPython_QMC5883P
Keywords: adafruit,blinka,circuitpython,micropython,qmc5883p,magnetometer,,sensor
Classifier: Intended Audience :: Developers
Classifier: Topic :: Software Development :: Libraries
Classifier: Topic :: Software Development :: Embedded Systems
Classifier: Topic :: System :: Hardware
Classifier: License :: OSI Approved :: MIT License
Classifier: Programming Language :: Python :: 3
License-File: LICENSE
Requires-Dist: Adafruit-Blinka
Requires-Dist: adafruit-circuitpython-busdevice
Requires-Dist: adafruit-circuitpython-register
Provides-Extra: optional
Dynamic: license-file
